{"cameraMode":{"drawMode":0,"name":"Shaded","section":"Shading Mode"},"sceneLighting":true,"audioPlay":false,"sceneViewState":{"showFog":true,"showMaterialUpdate":false,"showSkybox":true,"showFlares":true,"showImageEffects":true,"showParticleSystems":true},"in2DMode":false,"pivot":{"x":815.8222045898438,"y":-3.969142436981201,"z":717.6095581054688},"rotation":{"x":0.15118645131587983,"y":0.4409606456756592,"z":-0.0755271166563034,"w":0.8815228939056397},"size":29.766416549682618,"orthographic":false}